sloth_cli
