Metadata-Version: 2.1
Name: sloth-cli
Version: 1.1.1
Summary: A library to analyse how slow your code is. This is a quick way to validate what is slow in your code. 
Home-page: https://github.com/rigogsilva/sloth-cli
Author: Rodrigo da Silva
Author-email: dasil021@umn.edu
License: UNKNOWN
Keywords: cProfile,speed,cli,performance,slow
Platform: UNKNOWN
Classifier: Programming Language :: Python :: 3.6
Classifier: Programming Language :: Python :: 3.7
